mesa_llm/__init__.py
mesa_llm/llm_agent.py
mesa_llm/module_llm.py
mesa_llm/parallel_stepping.py
mesa_llm/memory/episodic_memory.py
mesa_llm/memory/lt_memory.py
mesa_llm/memory/memory.py
mesa_llm/memory/st_lt_memory.py
mesa_llm/memory/st_memory.py
mesa_llm/reasoning/cot.py
mesa_llm/reasoning/react.py
mesa_llm/reasoning/reasoning.py
mesa_llm/reasoning/rewoo.py
mesa_llm/recording/agent_analysis.py
mesa_llm/recording/record_model.py
mesa_llm/recording/simulation_recorder.py
mesa_llm/tools/inbuilt_tools.py
mesa_llm/tools/tool_decorator.py
mesa_llm/tools/tool_manager.py
mesa_llm-0.1.1.dist-info/METADATA
mesa_llm-0.1.1.dist-info/WHEEL
mesa_llm-0.1.1.dist-info/licenses/LICENSE
mesa_llm-0.1.1.dist-info/licenses/NOTICE
mesa_llm-0.1.1.dist-info/RECORD
